nyl/__init__.py
nyl/daemon.py
nyl/templating.py
nyl/templating_test.py
nyl/commands/__init__.py
nyl/commands/add.py
nyl/commands/crds.py
nyl/commands/new.py
nyl/commands/profile.py
nyl/commands/run.py
nyl/commands/secrets.py
nyl/commands/template.py
nyl/commands/tun.py
nyl/commands/tools/__init__.py
nyl/commands/tools/bcrypt.py
nyl/commands/tools/sops.py
nyl/generator/__init__.py
nyl/generator/components.py
nyl/generator/dispatch.py
nyl/generator/dispatch_test.py
nyl/generator/helmchart.py
nyl/generator/helmchart_test.py
nyl/generator/statefulsecret.py
nyl/profiles/__init__.py
nyl/profiles/config.py
nyl/profiles/config_test.py
nyl/profiles/kubeconfig.py
nyl/profiles/tunnel.py
nyl/project/config.py
nyl/resources/__init__.py
nyl/resources/applyset.py
nyl/resources/applyset_test.py
nyl/resources/helmchart.py
nyl/resources/helmchart_test.py
nyl/resources/placeholder.py
nyl/resources/postprocessor.py
nyl/resources/postprocessor_test.py
nyl/resources/statefulsecret.py
nyl/secrets/__init__.py
nyl/secrets/config.py
nyl/secrets/config_test.py
nyl/secrets/kubernetes.py
nyl/secrets/null.py
nyl/secrets/sops.py
nyl/secrets/sops_test.py
nyl/tools/__init__.py
nyl/tools/di.py
nyl/tools/fs.py
nyl/tools/fs_test.py
nyl/tools/kubectl.py
nyl/tools/kubernetes.py
nyl/tools/kvstore.py
nyl/tools/loads.py
nyl/tools/logging.py
nyl/tools/pyroscope.py
nyl/tools/shell.py
nyl/tools/testing.py
nyl/tools/typer.py
nyl/tools/types.py
nyl/tools/url.py
nyl/tools/yaml.py
nyl-0.10.5.dist-info/METADATA
nyl-0.10.5.dist-info/WHEEL
nyl-0.10.5.dist-info/entry_points.txt
nyl-0.10.5.dist-info/RECORD
