Metadata-Version: 2.4
Name: nyl
Version: 0.10.5
Summary: Advanced templating engine for Kubernetes and GitOps.
Author-email: Niklas Rosenstein <rosensteinniklas@gmail.com>
License: MIT
Requires-Python: >=3.11
Requires-Dist: bcrypt>=4.2.0
Requires-Dist: databind>=4.5.2
Requires-Dist: filelock>=3.15.4
Requires-Dist: jinja2>=3.1.4
Requires-Dist: kubernetes>=30.1.0
Requires-Dist: loguru>=0.7.2
Requires-Dist: nr-stream>=1.1.5
Requires-Dist: pyroscope-io>=0.8.11
Requires-Dist: pyyaml>=6.0.1
Requires-Dist: requests>=2.32.3
Requires-Dist: stablehash<0.3.0,>=0.2.1
Requires-Dist: structured-templates>=0.1.1
Requires-Dist: typer>=0.12.3
Requires-Dist: typing-extensions>=4.12.2
